plumedCommunications.cpython-311-darwin.so
plumedCommunications.pyi
plumedCommunications.cpython-313-darwin.so
plumedCommunications.cpython-314-darwin.so
plumedCommunications.cpython-312-darwin.so
hillclimber-0.1.7.dist-info/RECORD
hillclimber-0.1.7.dist-info/WHEEL
hillclimber-0.1.7.dist-info/entry_points.txt
hillclimber-0.1.7.dist-info/METADATA
hillclimber-0.1.7.dist-info/licenses/LICENSE
hillclimber/interfaces.py
hillclimber/pycv.py
hillclimber/virtual_atoms.py
hillclimber/analysis.py
hillclimber/metadynamics.py
hillclimber/actions.py
hillclimber/__init__.py
hillclimber/selectors.py
hillclimber/biases.py
hillclimber/opes.py
hillclimber/calc.py
hillclimber/cvs.py
hillclimber/nodes.py
plumed/_plumed_core.cpython-311-darwin.so
plumed/__init__.py
plumed/_plumed_core.cpython-312-darwin.so
plumed/_plumed_core.cpython-314-darwin.so
plumed/_plumed_core.cpython-313-darwin.so
plumed/_lib/bin/plumed
plumed/_lib/bin/plumed-patch
plumed/_lib/bin/plumed-config
plumed/_lib/include/plumed/secondarystructure/SecondaryStructureBase.h
plumed/_lib/include/plumed/mapping/Path.h
plumed/_lib/include/plumed/mapping/PathProjectionCalculator.h
plumed/_lib/include/plumed/adjmat/ContactMatrix.h
plumed/_lib/include/plumed/adjmat/AdjacencyMatrixBase.h
plumed/_lib/include/plumed/ves/VesTools.h
plumed/_lib/include/plumed/ves/GridIntegrationWeights.h
plumed/_lib/include/plumed/ves/CoeffsMatrix.h
plumed/_lib/include/plumed/ves/TargetDistModifer.h
plumed/_lib/include/plumed/ves/VesBias.h
plumed/_lib/include/plumed/ves/GridProjWeights.h
plumed/_lib/include/plumed/ves/BasisFunctions.h
plumed/_lib/include/plumed/ves/Optimizer.h
plumed/_lib/include/plumed/ves/CoeffsVector.h
plumed/_lib/include/plumed/ves/WaveletGrid.h
plumed/_lib/include/plumed/ves/TargetDistribution.h
plumed/_lib/include/plumed/ves/GridLinearInterpolation.h
plumed/_lib/include/plumed/ves/LinearBasisSetExpansion.h
plumed/_lib/include/plumed/ves/FermiSwitchingFunction.h
plumed/_lib/include/plumed/ves/CoeffsBase.h
plumed/_lib/include/plumed/isdb/MetainferenceBase.h
plumed/_lib/include/plumed/blas/real.h
plumed/_lib/include/plumed/blas/blas.h
