Metadata-Version: 2.4
Name: hillclimber
Version: 0.1.7
Summary: Python interfaces for the plumed library with enhanced sampling.
License: 		   GNU LESSER GENERAL PUBLIC LICENSE
License-File: LICENSE
Requires-Python: >=3.11
Requires-Dist: ase>=3.25.0
Requires-Dist: metadynminer>=0.9.1
Requires-Dist: molify>=0.2.0
Requires-Dist: rdkit2ase>=0.1.13
Requires-Dist: seaborn>=0.13.2
Requires-Dist: zntrack>=0.8.9
